textris/__init__.py
textris/main.py
textris-1.19.13.dist-info/METADATA
textris-1.19.13.dist-info/WHEEL
textris-1.19.13.dist-info/entry_points.txt
textris-1.19.13.dist-info/top_level.txt
textris-1.19.13.dist-info/RECORD
