Metadata-Version: 2.1
Name: textris
Version: 1.19.13
Summary: This is a simple Textual CLI Tetris Game designed for the command-line interface, featuring good 'ol Tetris gameplay mechanics using ASCII-based graphics. If it returns a EERerror increase your cmd width to at least 256.
Home-page: UNKNOWN
Author: YknotTYD
License: UNKNOWN
Platform: UNKNOWN
Requires-Dist: windows-curses (>=2.3.1)
Requires-Dist: keyboard (>=0.13.5)
Requires-Dist: art (>=6.1)
